README.rst
setup.py
Copreus.egg-info/PKG-INFO
Copreus.egg-info/SOURCES.txt
Copreus.egg-info/dependency_links.txt
Copreus.egg-info/entry_points.txt
Copreus.egg-info/requires.txt
Copreus.egg-info/top_level.txt
copreus/__init__.py
copreus/baseclasses/__init__.py
copreus/baseclasses/adriver.py
copreus/baseclasses/aepaper.py
copreus/baseclasses/aevents.py
copreus/baseclasses/ai2c.py
copreus/baseclasses/apolling.py
copreus/baseclasses/arotaryencoder.py
copreus/baseclasses/aspi.py
copreus/baseclasses/calibratedvalue.py
copreus/baseclasses/valuerange.py
copreus/drivermanager/__init__.py
copreus/drivermanager/driverfactory.py
copreus/drivermanager/drivermanager.py
copreus/drivers/__init__.py
copreus/drivers/adc.py
copreus/drivers/bme_280.py
copreus/drivers/dac.py
copreus/drivers/dht.py
copreus/drivers/epaperdirect.py
copreus/drivers/epapersimple.py
copreus/drivers/input.py
copreus/drivers/output.py
copreus/drivers/pollinginput.py
copreus/drivers/rfid.py
copreus/drivers/rgbled.py
copreus/drivers/rotaryencoder.py
copreus/drivers/rotaryencoder2.py
copreus/schema/__init__.py
copreus/schema/adc.py
copreus/schema/adriver.py
copreus/schema/aepaper.py
copreus/schema/apolling.py
copreus/schema/aspi.py
copreus/schema/bme_280.py
copreus/schema/calibratedvalue.py
copreus/schema/dac.py
copreus/schema/dht.py
copreus/schema/drivermanager.py
copreus/schema/epaperdirect.py
copreus/schema/epapersimple.py
copreus/schema/input.py
copreus/schema/output.py
copreus/schema/pollinginput.py
copreus/schema/rfid.py
copreus/schema/rgbled.py
copreus/schema/rotaryencoder.py
copreus/schema/rotaryencoder2.py
copreus/schema/valuerange.py
tests_manual/__init__.py
tests_manual/test_adc.py
tests_manual/test_adcdac.py
tests_manual/test_bme_280.py
tests_manual/test_dac.py
tests_manual/test_dht_continuos.py
tests_manual/test_dht_spontanuos.py
tests_manual/test_drivermanager.py
tests_manual/test_epaperdirect.py
tests_manual/test_epapersimple.py
tests_manual/test_input.py
tests_manual/test_output.py
tests_manual/test_pollinginput.py
tests_manual/test_rgbled.py
tests_manual/test_rotaryencoder.py
tests_manual/test_rotaryencoder2.py
tests_manual/tools.py
tests_unit/__init__.py
